d2x_cli/__about__.py
d2x_cli/__init__.py
d2x_cli/__main__.py
d2x_cli/api.py
d2x_cli/auth.py
d2x_cli/cli.py
d2x_cli/logger.py
d2x_cli/runtime.py
d2x_cli/utils.py
d2x_cli/commands/github.py
d2x_cli/commands/job.py
d2x_cli/commands/org.py
d2x_cli/commands/plan.py
d2x_cli/commands/repo.py
d2x_cli/commands/scratch.py
d2x_cli/commands/service.py
d2x_cli/commands/test.py
d2x_cli/files/d2x-job.yml
d2x_cli-0.0.3.dist-info/METADATA
d2x_cli-0.0.3.dist-info/WHEEL
d2x_cli-0.0.3.dist-info/entry_points.txt
d2x_cli-0.0.3.dist-info/licenses/LICENSE.txt
d2x_cli-0.0.3.dist-info/RECORD
